SpaceShare/__init__.py
SpaceShare/optimize_rideshares.py
SpaceShare/reader.py
SpaceShare/run.py
SpaceShare/write_email.py
SpaceShare-0.1.1.dist-info/LICENSE
SpaceShare-0.1.1.dist-info/METADATA
SpaceShare-0.1.1.dist-info/WHEEL
SpaceShare-0.1.1.dist-info/top_level.txt
SpaceShare-0.1.1.dist-info/RECORD
