Metadata-Version: 2.1
Name: SpaceShare
Version: 0.1.1
Summary: Package to schedule ride and hotel sharing
Home-page: https://github.com/sheydenreich/SpaceShare
License-File: LICENSE
Requires-Dist: numpy
Requires-Dist: pandas
Requires-Dist: scipy
Requires-Dist: configparser
